sklearn_to_pfa/__init__.py
sklearn_to_pfa/featurizer.py
sklearn_to_pfa/mixed_nb.py
sklearn_to_pfa/sklearn_to_pfa.py
sklearn_to_pfa-0.3.10.dist-info/DESCRIPTION.rst
sklearn_to_pfa-0.3.10.dist-info/METADATA
sklearn_to_pfa-0.3.10.dist-info/RECORD
sklearn_to_pfa-0.3.10.dist-info/WHEEL
sklearn_to_pfa-0.3.10.dist-info/metadata.json
sklearn_to_pfa-0.3.10.dist-info/top_level.txt
tests/__init__.py
tests/test_featurizer.py
tests/test_mixed_nb.py
tests/test_pfa_sklearn.py
