Metadata-Version: 2.0
Name: sklearn-to-pfa
Version: 0.3.10
Summary: Convert scikit-learn models to PFA
Home-page: https://github.com/LREN-CHUV/python-base-docker-images
Author: Mojmir Vinkler
Author-email: UNKNOWN
License: Apache 2.0
Platform: UNKNOWN
Classifier: Intended Audience :: Developers
Classifier: Intended Audience :: Science/Research
Classifier: Operating System :: Unix
Classifier: License :: OSI Approved :: Apache Software License
Classifier: Topic :: Scientific/Engineering :: Bio-Informatics
Classifier: Programming Language :: Python :: 3 :: Only
Classifier: Programming Language :: Python :: 3.6
Requires-Dist: pandas
Requires-Dist: scikit-learn
Requires-Dist: scipy
Provides-Extra: test
Requires-Dist: nose; extra == 'test'
Requires-Dist: unittest; extra == 'test'
